[
{"hsn":"55","description":"Man-made staple fibres"},
{"hsn":"5501","description":"SYNTHETIC FILAMENT TOW"},
{"hsn":"55011000","description":"SYNTHETIC FILAMENT TOW - OF NYLON OR OTHER POLYAMIDES"},
{"hsn":"550111","description":"OF ARAMIDES"},
{"hsn":"55011100","description":"OF ARAMIDES"},
{"hsn":"550119","description":"OTHER"},
{"hsn":"55011900","description":"OTHER"},
{"hsn":"550120","description":"OF POLYESTERS"},
{"hsn":"55012000","description":"OF POLYESTERS"},
{"hsn":"550130","description":"ACRYLIC OR MODACRYLIC"},
{"hsn":"55013000","description":"ACRYLIC OR MODACRYLIC"},
{"hsn":"550140","description":"OF POLYPROPYLENE"},
{"hsn":"55014000","description":"OF POLYPROPYLENE"},
{"hsn":"550190","description":"OTHER :"},
{"hsn":"55019010","description":"OF POLYPROPYLENE"},
{"hsn":"55019090","description":"OTHER"},
{"hsn":"5502","description":"ARTIFICIAL FILAMENT TOW"},
{"hsn":"550200","description":"Artificial filament tow"},
{"hsn":"55020010","description":"ARTIFICIAL FILAMENT TOW - ARTIFICIAL FILAMENT TOW : ACETATE RAYON TOW"},
{"hsn":"55020020","description":"ARTIFICIAL FILAMENT TOW - ARTIFICIAL FILAMENT TOW : VISCOSE RAYON TOW"},
{"hsn":"55020090","description":"ARTIFICIAL FILAMENT TOW - ARTIFICIAL FILAMENT TOW : OTHER"},
{"hsn":"550210","description":"OF CELLULOSE ACETATE:"},
{"hsn":"55021010","description":"Viscose rayon tow"},
{"hsn":"55021090","description":"Other"},
{"hsn":"550290","description":"OTHER:"},
{"hsn":"55029010","description":"Viscose rayon tow"},
{"hsn":"55029090","description":"other"},
{"hsn":"5503","description":"SYNTHETIC STAPLE FIBRES, NOT CARDED, COMBED OR OTHERWISE PROCESSED FOR SPINNING"},
{"hsn":"55031000","description":"SYNTHETIC STAPLE FIBRES, NOT CARDED, COMBED OR OTHERWISE PROCESSED FOR SPINNING - OF NYLON OR OTHER POLYAMIDES"},
{"hsn":"550311","description":"Of aramids:"},
{"hsn":"55031100","description":"SYNTHETIC STAPLE FIBRES, NOT CARDED, COMBED OR OTHERWISE PROCESSED FOR SPINNING - OF NYLON OR OTHER POLYAMIDES - OF ARAMIDES"},
{"hsn":"55031110","description":"Aramid Flame Retardant Fibre"},
{"hsn":"55031120","description":"PARA-ARAMID FIBRE"},
{"hsn":"55031190","description":"OTHER"},
{"hsn":"550319","description":"Other:"},
{"hsn":"55031900","description":"SYNTHETIC STAPLE FIBRES, NOT CARDED, COMBED OR OTHERWISE PROCESSED FOR SPINNING - OF NYLON OR OTHER POLYAMIDES-OTHERS"},
{"hsn":"55031910","description":"Nylon Staple Fibre"},
{"hsn":"55031920","description":"Nylon Anti Static Staple Fibre"},
{"hsn":"55031930","description":"NYLON 66 FIBRE CONFORMING TO IS 13463"},
{"hsn":"55031990","description":"Other"},
{"hsn":"550320","description":"OF POLYESTERS"},
{"hsn":"55032000","description":"OF POLYESTERS"},
{"hsn":"550330","description":"Acrylic or modacrylic:"},
{"hsn":"55033000","description":"SYNTHETIC STAPLE FIBRES, NOT CARDED, COMBED OR OTHERWISE PROCESSED FOR SPINNING - ACRYLIC OR MODACRYLIC"},
{"hsn":"55033010","description":"Pre Oxidised Fibre, conforming to IS 17308"},
{"hsn":"55033090","description":"Other"},
{"hsn":"550340","description":"OF POLYPROPYLENE"},
{"hsn":"55034000","description":"OF POLYPROPYLENE"},
{"hsn":"550390","description":"OTHER :"},
{"hsn":"55039010","description":"POLYVINYL STAPLE FIBRE"},
{"hsn":"55039020","description":"POLYVINYL CHLORIDE STAPLE FIBRE"},
{"hsn":"55039030","description":"Ultra high molecular weight poly ethylene staple fibre conforming to ASTM F2848"},
{"hsn":"55039090","description":"OTHER"},
{"hsn":"5504","description":"ARTIFICIAL STAPLE FIBRES, NOT CARDED, COMBED OR OTHERWISE PROCESSED FOR SPINNING"},
{"hsn":"550410","description":"OF VISCOSE RAYON:"},
{"hsn":"55041000","description":"ARTIFICIAL STAPLE FIBRES, NOT CARDED, COMBED OR OTHERWISE PROCESSED FOR SPINNING - OF VISCOSE RAYON"},
{"hsn":"55041010","description":"Obtained from wood other than bamboo"},
{"hsn":"55041011","description":"Flame retaradant Viscose Rayon fibre"},
{"hsn":"55041019","description":"Other"},
{"hsn":"55041020","description":"Obtained from bamboo"},
{"hsn":"55041021","description":"Flame retaradant Viscose Rayon fibre"},
{"hsn":"55041029","description":"Other"},
{"hsn":"55041090","description":"Other"},
{"hsn":"550490","description":"OTHER :"},
{"hsn":"55049010","description":"ACETATE RAYON STAPLE FIBRE"},
{"hsn":"55049020","description":"POLYNOSIC STAPLE FIBRE"},
{"hsn":"55049030","description":"HIGH WET MODULUS STAPLE FIBRE"},
{"hsn":"55049090","description":"OTHER"},
{"hsn":"5505","description":"WASTE (INCLUDING NOILS, YARN WASTE AND GARNETTED STOCK) OF MAN-MADE FIBRES"},
{"hsn":"550510","description":"OF SYNTHETIC FIBERS :"},
{"hsn":"55051010","description":"OF ACRYLIC"},
{"hsn":"55051090","description":"OTHER"},
{"hsn":"550520","description":"OF ARTIFICIAL FIBRES"},
{"hsn":"55052000","description":"OF ARTIFICIAL FIBRES"},
{"hsn":"5506","description":"SYNTHETIC STAPLE FIBRES, CARDED COMBED OR OTHERWISE PROCESSED FOR SPINNING"},
{"hsn":"550610","description":"OF NYLON OR OTHER POLYAMIDES"},
{"hsn":"55061000","description":"OF NYLON OR OTHER POLYAMIDES"},
{"hsn":"550620","description":"OF POLYESTERS"},
{"hsn":"55062000","description":"OF POLYESTERS"},
{"hsn":"550630","description":"ACRYLIC OR MODACRYLIC"},
{"hsn":"55063000","description":"ACRYLIC OR MODACRYLIC"},
{"hsn":"550640","description":"OF POLYPROPYLENE"},
{"hsn":"55064000","description":"Of polypropylene"},
{"hsn":"550690","description":"OTHER :"},
{"hsn":"55069010","description":"POLYPROPYLENE TOPS"},
{"hsn":"55069090","description":"OTHER"},
{"hsn":"5507","description":"ARTIFICIAL STAPLE FIBRES, CARDED, COMBED OR OTHERWISE PROCESSED FOR SPINNING"},
{"hsn":"550700","description":"ARTIFICIAL STAPLE FIBRES, CARDED, COMBED OR OTHERWISE PROCESSED FOR SPINNING :"},
{"hsn":"55070010","description":"ACETATE RAYON TOPS"},
{"hsn":"55070020","description":"VISCOSE TOPS"},
{"hsn":"55070030","description":"POLYNOSIC TOPS"},
{"hsn":"55070040","description":"HIGH WET MODULUS TOPS"},
{"hsn":"55070090","description":"OTHER"},
{"hsn":"5508","description":"SEWING THREAD OF MAN-MADE STAPLE FIBRES, WHETHER OR NOT PUT UP FOR RETAIL SALE"},
{"hsn":"550810","description":"OF SYNTHETIC STAPLE FIBRES"},
{"hsn":"55081000","description":"OF SYNTHETIC STAPLE FIBRES"},
{"hsn":"550820","description":"OF ARTIFICIAL STAPLE FIBRES"},
{"hsn":"55082000","description":"OF ARTIFICIAL STAPLE FIBRES"},
{"hsn":"5509","description":"YARN (OTHER THAN SEWING THREAD) OF SYNTHETIC STAPLE FIBRES, NOT PUT UP FOR RETAIL SALE"},
{"hsn":"550911","description":"SINGLE YARN"},
{"hsn":"55091100","description":"SINGLE YARN"},
{"hsn":"550912","description":"MULTIPLE (FOLDED) OR CABLED YARN"},
{"hsn":"55091200","description":"MULTIPLE (FOLDED) OR CABLED        YARN"},
{"hsn":"550921","description":"SINGLE YARN"},
{"hsn":"55092100","description":"SINGLE YARN"},
{"hsn":"550922","description":"MULTIPLE (FOLDED) OR CABLED YARN"},
{"hsn":"55092200","description":"MULTIPLE (FOLDED) OR CABLED            YARN"},
{"hsn":"550931","description":"SINGLE YARN"},
{"hsn":"55093100","description":"SINGLE YARN"},
{"hsn":"550932","description":"MULTIPLE (FOLDED) OR CABLED YARN"},
{"hsn":"55093200","description":"MULTIPLE (FOLDED) OR CABLED            YARN"},
{"hsn":"550941","description":"SINGLE YARN :"},
{"hsn":"55094110","description":"POLYPROPYLENE SPUN YARN"},
{"hsn":"55094120","description":"POLYVINYL ACETATE SPUN YARN"},
{"hsn":"55094130","description":"POLYVINYL CHLORIDE SPUN YARN"},
{"hsn":"55094190","description":"OTHER"},
{"hsn":"550942","description":"MULTIPLE (FOLDED) OR CABLED YARN :"},
{"hsn":"55094210","description":"POLYPROPYLENE SPUN YARN"},
{"hsn":"55094220","description":"POLYVINYL ACETATE (PVA) SPUN YARN"},
{"hsn":"55094230","description":"POLYVINYL CHLORIDE (PVC) SPUN YARN"},
{"hsn":"55094290","description":"OTHER"},
{"hsn":"550951","description":"MIXED MAINLY OR SOLELY WITH ARTIFICIAL STAPLE FIBRES"},
{"hsn":"55095100","description":"MIXED MAINLY OR SOLELY WITH ARTIFICIAL STAPLE FIBRES"},
{"hsn":"550952","description":"MIXED MAINLY OR SOLELY WITH WOOL OR FINE ANIMAL HAIR"},
{"hsn":"55095200","description":"MIXED MAINLY OR SOLELY WITH WOOL OR FINE ANIMAL HAIR"},
{"hsn":"550953","description":"MIXED MAINLY OR SOLELY WITH COTTON"},
{"hsn":"55095300","description":"MIXED MAINLY OR SOLELY WITH COTTON"},
{"hsn":"550959","description":"OTHER"},
{"hsn":"55095900","description":"OTHER"},
{"hsn":"550961","description":"MIXED MAINLY OR SOLELY WITH WOOL OR FINE ANIMAL HAIR"},
{"hsn":"55096100","description":"MIXED MAINLY OR SOLELY WITH WOOL OR FINE ANIMAL HAIR"},
{"hsn":"550962","description":"MIXED MAINLY OR SOLELY WITH COTTON"},
{"hsn":"55096200","description":"MIXED MAINLY OR SOLELY WITH COTTON"},
{"hsn":"550969","description":"OTHER"},
{"hsn":"55096900","description":"OTHER"},
{"hsn":"550991","description":"MIXED MAINLY OR SOLELY WITH WOOL OR FINE ANIMAL HAIR"},
{"hsn":"55099100","description":"MIXED MAINLY OR SOLELY WITH WOOL OR FINE ANIMAL HAIR"},
{"hsn":"550992","description":"MIXED MAINLY OR SOLELY WITH COTTON"},
{"hsn":"55099200","description":"MIXED MAINLY OR SOLELY WITH COTTON"},
{"hsn":"550999","description":"Other:"},
{"hsn":"55099900","description":"YARN (OTHER THAN SEWING THREAD) OF SYNTHETIC STAPLE FIBRES, NOT PUT UP FOR RETAIL SALE - OTHER YARN : OTHER"},
{"hsn":"55099910","description":"Yarn made of 100% inherent FR synthetic fibre"},
{"hsn":"55099990","description":"Other"},
{"hsn":"5510","description":"YARN (OTHER THAN SEWING THREAD) OF ARTIFICIAL STAPLE FIBRES, NOT PUT UP FOR RETAIL SALE"},
{"hsn":"551011","description":"SINGLE YARN :"},
{"hsn":"55101110","description":"VISCOSE RAYON SPUN YARN"},
{"hsn":"55101120","description":"ACETATE RAYON SPUN YARN"},
{"hsn":"55101190","description":"OTHER"},
{"hsn":"551012","description":"MULTIPLE (FOLDED) OR CABLED  YARN:"},
{"hsn":"55101210","description":"VISCOSE RAYON SPUN YARN"},
{"hsn":"55101220","description":"ACETATE RAYON SPUN YARN"},
{"hsn":"55101290","description":"OTHER"},
{"hsn":"551020","description":"OTHER YARN, MIXED MAINLY OR SOLELY WITH WOOL OR FINE ANIMAL HAIR :"},
{"hsn":"55102010","description":"VISCOSE RAYON SPUN YARN"},
{"hsn":"55102020","description":"ACETATE RAYON SPUN YARN"},
{"hsn":"55102090","description":"OTHER"},
{"hsn":"551030","description":"OTHER YARN, MIXED MAINLY OR SOLELY WITH COTTON :"},
{"hsn":"55103010","description":"VISCOSE RAYON SPUN YARN"},
{"hsn":"55103020","description":"ACETATE RAYON SPUN YARN"},
{"hsn":"55103090","description":"OTHER"},
{"hsn":"551090","description":"OTHER YARN :"},
{"hsn":"55109010","description":"VISCOSE RAYON SPUN YARN"},
{"hsn":"55109020","description":"ACETATE RAYON SPUN YARN"},
{"hsn":"55109030","description":"Yarn made of 100% inherent FR artificial fibre"},
{"hsn":"55109090","description":"OTHER"},
{"hsn":"5511","description":"YARN (OTHER THAN SEWING THREAD) OF MAN-MADE STAPLE FIBRES, PUT UP FOR RETAIL SALE"},
{"hsn":"551110","description":"OF SYNTHETIC STAPLE FIBRES, CONTAINING 85% OR MORE BY WEIGHT OF SUCH FIBRES"},
{"hsn":"55111000","description":"OF SYNTHETIC STAPLE FIBRES, CONTAINING 85% OR MORE BY WEIGHT OF SUCH FIBRES"},
{"hsn":"551120","description":"OF SYNTHETIC STAPLE FIBRES, CONTAINING LESS THAN 85% BY WEIGHT OF SUCH FIBRES"},
{"hsn":"55112000","description":"OF SYNTHETIC STAPLE FIBRES, CONTAINING LESS THAN 85% BY WEIGHT OF SUCH FIBRES"},
{"hsn":"551130","description":"OF ARTIFICIAL STAPLE FIBRES :"},
{"hsn":"55113010","description":"CONTAINING MORE THAN 85% BY WEIGHT OF STAPLE FIBRE"},
{"hsn":"55113090","description":"OTHER"},
{"hsn":"5512","description":"WOVEN FABRICS OF SYNTHETIC STAPLE FIBRES, CONTAINING 85% OR MORE BY WEIGHT OF SYNTHETIC STAPLE FIBRES"},
{"hsn":"551211","description":"UNBLEACHED OR BLEACHED :"},
{"hsn":"55121110","description":"UNBLEACHED"},
{"hsn":"55121120","description":"BLEACHED"},
{"hsn":"551219","description":"OTHER :"},
{"hsn":"55121910","description":"DYED"},
{"hsn":"55121920","description":"PRINTED"},
{"hsn":"55121990","description":"OTHER"},
{"hsn":"551221","description":"UNBLEACHED OR BLEACHED :"},
{"hsn":"55122110","description":"UNBLEACHED"},
{"hsn":"55122120","description":"BLEACHED"},
{"hsn":"551229","description":"OTHER :"},
{"hsn":"55122910","description":"DYED"},
{"hsn":"55122920","description":"PRINTED"},
{"hsn":"55122990","description":"OTHER"},
{"hsn":"551291","description":"UNBLEACHED OR BLEACHED :"},
{"hsn":"55129110","description":"UNBLEACHED"},
{"hsn":"55129120","description":"BLEACHED"},
{"hsn":"551299","description":"OTHER :"},
{"hsn":"55129910","description":"DYED"},
{"hsn":"55129920","description":"PRINTED"},
{"hsn":"55129990","description":"OTHER"},
{"hsn":"5513","description":"WOVEN FABRICS OF SYNTHETIC STAPLE FIBRES, CONTAINING LESS THAN 85% BY WEIGHT OF SUCH FIBRES, MIXED MAINLY OR SOLELY WITH COTTON, OF A WEIGHT NOT EXCEEDING 170 G/M1"},
{"hsn":"551311","description":"OF POLYESTER STAPLE FIBRES, PLAIN WEAVE :"},
{"hsn":"55131110","description":"UNBLEACHED"},
{"hsn":"55131120","description":"BLEACHED"},
{"hsn":"551312","description":"3-THREAD OR 4-THREAD TWILL, INCLUDING CROSS TWILL, OF POLYESTER STAPLE FIBRES :"},
{"hsn":"55131210","description":"UNBLEACHED"},
{"hsn":"55131220","description":"BLEACHED"},
{"hsn":"551313","description":"OTHER WOVEN FABRICS OF POLYESTER STAPLE FIBRES :"},
{"hsn":"55131310","description":"UNBLEACHED"},
{"hsn":"55131320","description":"BLEACHED"},
{"hsn":"551319","description":"OTHER WOVEN FABRICS :"},
{"hsn":"55131910","description":"UNBLEACHED"},
{"hsn":"55131920","description":"BLEACHED"},
{"hsn":"551321","description":"OF POLYESTER STAPLE FIBRES, PLAIN WEAVE"},
{"hsn":"55132100","description":"OF POLYESTER STAPLE FIBRES, PLAIN WEAVE"},
{"hsn":"55132200","description":"WOVEN FABRICS OF SYNTHETIC STAPLE FIBRES, CONTAINING LESS THAN 85% BY WEIGHT OF SUCH FIBRES, MIXED MAINLY OR SOLELY WITH COTTON, OF A WEIGHT NOT EXCEEDING 170 G/M2 - DYED : 3-THREAD OR 4-THREAD TWILL, INCLUDING CROSS TWILL, OF POLYESTER STAPLE FIBRES"},
{"hsn":"551323","description":"OTHER WOVEN FABRICS OF  POLYESTER STAPLE FIBRES"},
{"hsn":"55132300","description":"OTHER WOVEN FABRICS OF  POLYESTER STAPLE FIBRES"},
{"hsn":"551329","description":"OTHER WOVEN FABRICS"},
{"hsn":"55132900","description":"OTHER WOVEN FABRICS"},
{"hsn":"551331","description":"OF POLYESTER STAPLE FIBRES, PLAIN WEAVE"},
{"hsn":"55133100","description":"OF POLYESTER STAPLE FIBRES,PLAIN WEAVE"},
{"hsn":"55133200","description":"WOVEN FABRICS OF SYNTHETIC STAPLE FIBRES, CONTAINING LESS THAN 85% BY WEIGHT OF SUCH FIBRES, MIXED MAINLY OR SOLELY WITH COTTON, OF A WEIGHT NOT EXCEEDING 170 G/M2 - OF YARNS OF DIFFERENT COLOURS : 3-THREAD OR 4-THREAD TWILL, INCLUDING CROSS TWILL, OF POLYESTER STAPLE FIBRES"},
{"hsn":"55133300","description":"WOVEN FABRICS OF SYNTHETIC STAPLE FIBRES, CONTAINING LESS THAN 85% BY WEIGHT OF SUCH FIBRES, MIXED MAINLY OR SOLELY WITH COTTON, OF A WEIGHT NOT EXCEEDING 170 G/M2 - OF YARNS OF DIFFERENT COLOURS : OTHER WOVEN FABRICS OF POLYESTER STAPLE FIBRES"},
{"hsn":"551339","description":"OTHER WOVEN FABRICS"},
{"hsn":"55133900","description":"OTHER WOVEN FABRICS"},
{"hsn":"551341","description":"OF POLYESTER STAPLE FIBRES, PLAIN WEAVE"},
{"hsn":"55134100","description":"OF POLYESTER STAPLE FIBRES, PLAIN WEAVE"},
{"hsn":"55134200","description":"WOVEN FABRICS OF SYNTHETIC STAPLE FIBRES, CONTAINING LESS THAN 85% BY WEIGHT OF SUCH FIBRES, MIXED MAINLY OR SOLELY WITH COTTON, OF A WEIGHT NOT EXCEEDING 170 G/M2 - PRINTED : 3-THREAD OR 4-THREAD TWILL, INCLUDING CROSS TWILL, OF POLYESTER STAPLE FIBRES"},
{"hsn":"55134300","description":"WOVEN FABRICS OF SYNTHETIC STAPLE FIBRES, CONTAINING LESS THAN 85% BY WEIGHT OF SUCH FIBRES, MIXED MAINLY OR SOLELY WITH COTTON, OF A WEIGHT NOT EXCEEDING 170 G/M2 - PRINTED : OTHER WOVEN FABRICS OF POLYESTER STAPLE FIBRES"},
{"hsn":"551349","description":"OTHER WOVEN FABRIC."},
{"hsn":"55134900","description":"OTHER WOVEN FABRIC."},
{"hsn":"5514","description":"WOVEN FABRICS OF SYNTHETIC STAPLE FIBRES, CONTAINING LESS THAN 85% BY WEIGHT OF SUCH FIBRES, MIXED MAINLY OR SOLELY WITH COTTON, OF A WEIGHT EXCEEDING 170 G/M1"},
{"hsn":"551411","description":"OF POLYESTER STAPLE FIBRES, PLAIN WEAVE :"},
{"hsn":"55141110","description":"UNBLEACHED"},
{"hsn":"55141120","description":"BLEACHED"},
{"hsn":"551412","description":"3-THREAD OR 4-THREAD TWILL, INCLUDING CROSS TWILL, OF POLYESTER STAPLE FIBRES :"},
{"hsn":"55141210","description":"UNBLEACHED"},
{"hsn":"55141220","description":"BLEACHED"},
{"hsn":"55141310","description":"WOVEN FABRICS OF SYNTHETIC STAPLE FIBRES, CONTAINING LESS THAN 85% BY WEIGHT OF SUCH FIBRES, MIXED MAINLY OR SOLELY WITH COTTON, OF A WEIGHT EXCEEDING 170 G/M2 - UNBLEACHED OR BLEACHED : OTHER WOVEN FABRICS OF POLYESTER STAPLE FIBRES : UNBLEACHED"},
{"hsn":"55141320","description":"WOVEN FABRICS OF SYNTHETIC STAPLE FIBRES, CONTAINING LESS THAN 85% BY WEIGHT OF SUCH FIBRES, MIXED MAINLY OR SOLELY WITH COTTON, OF A WEIGHT EXCEEDING 170 G/M2 - UNBLEACHED OR BLEACHED : OTHER WOVEN FABRICS OF POLYESTER STAPLE FIBRES : BLEACHED"},
{"hsn":"551419","description":"OTHER :"},
{"hsn":"55141910","description":"UNBLEACHED"},
{"hsn":"55141920","description":"BLEACHED"},
{"hsn":"551421","description":"OF POLYESTER STAPLE FIBRES, PLAIN WEAVE"},
{"hsn":"55142100","description":"OF POLYESTER STAPLE FIBRES, PLAIN WEAVE"},
{"hsn":"551422","description":"3-THREAD OR 4-THREAD TWILL, INCLUDING CROSS TWILL, OF POLYESTER STAPLE FIBRES"},
{"hsn":"55142200","description":"3-THREAD OR 4-THREAD TWILL, INCLUDING CROSS TWILL, OF POLYESTER STAPLE FIBRES"},
{"hsn":"551423","description":"OTHER WOVEN FABRICS OF  POLYESTER STAPLE FIBRES"},
{"hsn":"55142300","description":"OTHER WOVEN FABRICS OF  POLYESTER STAPLE FIBRES"},
{"hsn":"551429","description":"OTHER WOVEN FABRICS"},
{"hsn":"55142900","description":"OTHER WOVEN FABRICS"},
{"hsn":"551430","description":"OF YARNS OF DIFFERENT COLOURS :"},
{"hsn":"55143011","description":"OF POLYESTER STAPLE FIBRES, PLAIN WEAVE"},
{"hsn":"55143012","description":"3-THREAD OR 4-THREAD TWILL, INCLUDING CROSS TWILL, OF POLYESTER STAPLE FIBRES"},
{"hsn":"55143013","description":"OTHER WOVEN FABRICS OF POLYESTER STAPLE FIBRES"},
{"hsn":"55143019","description":"OTHER WOVEN FABRICS"},
{"hsn":"55143100","description":"WOVEN FABRICS OF SYNTHETIC STAPLE FIBRES, CONTAINING LESS THAN 85% BY WEIGHT OF SUCH FIBRES, MIXED MAINLY OR SOLELY WITH COTTON, OF A WEIGHT EXCEEDING 170 G/M2 - OF YARNS OF DIFFERENT COLOURS : OF POLYESTER STAPLE FIBRES, PLAIN WEAVE"},
{"hsn":"55143200","description":"WOVEN FABRICS OF SYNTHETIC STAPLE FIBRES, CONTAINING LESS THAN 85% BY WEIGHT OF SUCH FIBRES, MIXED MAINLY OR SOLELY WITH COTTON, OF A WEIGHT EXCEEDING 170 G/M2 - OF YARNS OF DIFFERENT COLOURS : 3-THREAD OR 4-THREAD TWILL, INCLUDING CROSS TWILL, OF POLYESTER STAPLE FIBRES"},
{"hsn":"55143300","description":"WOVEN FABRICS OF SYNTHETIC STAPLE FIBRES, CONTAINING LESS THAN 85% BY WEIGHT OF SUCH FIBRES, MIXED MAINLY OR SOLELY WITH COTTON, OF A WEIGHT EXCEEDING 170 G/M2 - OF YARNS OF DIFFERENT COLOURS : OTHER WOVEN FABRICS OF POLYESTER STAPLE FIBRES"},
{"hsn":"55143900","description":"WOVEN FABRICS OF SYNTHETIC STAPLE FIBRES, CONTAINING LESS THAN 85% BY WEIGHT OF SUCH FIBRES, MIXED MAINLY OR SOLELY WITH COTTON, OF A WEIGHT EXCEEDING 170 G/M2 - OF YARNS OF DIFFERENT COLOURS : OTHER WOVEN FABRICS"},
{"hsn":"551441","description":"OF POLYESTER STAPLE FIBRES, PLAIN WEAVE"},
{"hsn":"55144100","description":"OF POLYESTER STAPLE FIBRES, PLAIN WEAVE"},
{"hsn":"551442","description":"3-THREAD OR 4-THREAD TWILL, INCLUDING CROSS TWILL, OF POLYESTER STAPLE FIBRES"},
{"hsn":"55144200","description":"3-THREAD OR 4-THREAD TWILL, INCLUDING CROSS TWILL, OF POLYESTER STAPLE FIBRES"},
{"hsn":"551443","description":"OTHER WOVEN FABRICS OF POLYESTER STAPLE FIBRES"},
{"hsn":"55144300","description":"OTHER WOVEN FABRICS OF POLYESTER STAPLE FIBRES"},
{"hsn":"551449","description":"OTHER WOVEN FABRICS"},
{"hsn":"55144900","description":"OTHER WOVEN FABRICS"},
{"hsn":"5515","description":"OTHER WOVEN FABRICS OF SYNTHETIC STAPLE FIBRES"},
{"hsn":"551511","description":"MIXED MAINLY OR SOLELY WITH VISCOS RAYON STAPLE FIBRES :"},
{"hsn":"55151110","description":"UNBLEACHED"},
{"hsn":"55151120","description":"BLEACHED"},
{"hsn":"55151130","description":"DYED"},
{"hsn":"55151140","description":"PRINTED"},
{"hsn":"55151190","description":"OTHER"},
{"hsn":"551512","description":"MIXED MAINLY OR SOLELY WITH MAN-MADE FILAMENTS :"},
{"hsn":"55151210","description":"UNBLEACHED"},
{"hsn":"55151220","description":"BLEACHED"},
{"hsn":"55151230","description":"DYED"},
{"hsn":"55151240","description":"PRINTED"},
{"hsn":"55151290","description":"OTHER"},
{"hsn":"551513","description":"MIXED MAINLY OR SOLELY WITH WOOL OR FINE ANIMAL HAIR :"},
{"hsn":"55151310","description":"UNBLEACHED"},
{"hsn":"55151320","description":"BLEACHED"},
{"hsn":"55151330","description":"DYED"},
{"hsn":"55151340","description":"PRINTED"},
{"hsn":"55151390","description":"OTHER"},
{"hsn":"551519","description":"OTHER:"},
{"hsn":"55151910","description":"UNBLEACHED"},
{"hsn":"55151920","description":"BLEACHED"},
{"hsn":"55151930","description":"DYED"},
{"hsn":"55151940","description":"PRINTED"},
{"hsn":"55151990","description":"OTHER"},
{"hsn":"551521","description":"MIXED MAINLY OR SOLELY WITH MAN-MADE FILAMENTS :"},
{"hsn":"55152110","description":"UNBLEACHED"},
{"hsn":"55152120","description":"BLEACHED"},
{"hsn":"55152130","description":"DYED"},
{"hsn":"55152140","description":"PRINTED"},
{"hsn":"55152190","description":"OTHER"},
{"hsn":"551522","description":"MIXED MAINLY OR SOLELY WITH WOOL OR FINE ANIMAL HAIR :"},
{"hsn":"55152210","description":"UNBLEACHED"},
{"hsn":"55152220","description":"BLEACHED"},
{"hsn":"55152230","description":"DYED"},
{"hsn":"55152240","description":"PRINTED"},
{"hsn":"55152290","description":"OTHER"},
{"hsn":"551529","description":"OTHER :"},
{"hsn":"55152910","description":"UNBLEACHED"},
{"hsn":"55152920","description":"BLEACHED"},
{"hsn":"55152930","description":"DYED"},
{"hsn":"55152940","description":"PRINTED"},
{"hsn":"55152990","description":"OTHER"},
{"hsn":"551591","description":"MIXED MAINLY OR SOLELY WITH MAN-MADE FILAMENTS :"},
{"hsn":"55159110","description":"UNBLEACHED"},
{"hsn":"55159120","description":"BLEACHED"},
{"hsn":"55159130","description":"DYED"},
{"hsn":"55159140","description":"PRINTED"},
{"hsn":"55159190","description":"OTHER"},
{"hsn":"55159210","description":"OTHER WOVEN FABRICS OF SYNTHETIC STAPLE FIBRES - OTHER WOVEN FABRICS : MIXED MAINLY OR SOLELY WITH WOOL OR FINE ANIMAL HAIR : UNBLEACHED"},
{"hsn":"55159220","description":"OTHER WOVEN FABRICS OF SYNTHETIC STAPLE FIBRES - OTHER WOVEN FABRICS : MIXED MAINLY OR SOLELY WITH WOOL OR FINE ANIMAL HAIR : BLEACHED"},
{"hsn":"55159230","description":"OTHER WOVEN FABRICS OF SYNTHETIC STAPLE FIBRES - OTHER WOVEN FABRICS : MIXED MAINLY OR SOLELY WITH WOOL OR FINE ANIMAL HAIR : DYED"},
{"hsn":"55159240","description":"OTHER WOVEN FABRICS OF SYNTHETIC STAPLE FIBRES - OTHER WOVEN FABRICS : MIXED MAINLY OR SOLELY WITH WOOL OR FINE ANIMAL HAIR : PRINTED"},
{"hsn":"55159290","description":"OTHER WOVEN FABRICS OF SYNTHETIC STAPLE FIBRES - OTHER WOVEN FABRICS : MIXED MAINLY OR SOLELY WITH WOOL OR FINE ANIMAL HAIR : OTHER"},
{"hsn":"551599","description":"OTHER :"},
{"hsn":"55159910","description":"UNBLEACHED"},
{"hsn":"55159920","description":"BLEACHED"},
{"hsn":"55159930","description":"DYED"},
{"hsn":"55159940","description":"PRINTED"},
{"hsn":"55159950","description":"FABRICS MADE OF 100% INHERENT FR SYNTHETIC FIBRE"},
{"hsn":"55159990","description":"OTHER"},
{"hsn":"5516","description":"WOVEN FABRICS OF ARTIFICIAL STAPLE FIBRES"},
{"hsn":"551611","description":"UNBLEACHED OR BLEACHED :"},
{"hsn":"55161110","description":"UNBLEACHED"},
{"hsn":"55161120","description":"BLEACHED"},
{"hsn":"551612","description":"DYED"},
{"hsn":"55161200","description":"DYED"},
{"hsn":"551613","description":"OF YARNS OF DIFFERENT COLOURS"},
{"hsn":"55161300","description":"OF YARNS OF DIFFERENT COLOURS"},
{"hsn":"551614","description":"PRINTED :"},
{"hsn":"55161410","description":"SPUN RAYON PRINTED SHANTUNG"},
{"hsn":"55161420","description":"SPUN RAYON PRINTED LINEN"},
{"hsn":"55161490","description":"OTHER"},
{"hsn":"551621","description":"UNBLEACHED OR BLEACHED :"},
{"hsn":"55162110","description":"UNBLEACHED"},
{"hsn":"55162120","description":"BLEACHED"},
{"hsn":"551622","description":"DYED"},
{"hsn":"55162200","description":"DYED"},
{"hsn":"551623","description":"OF YARNS OF DIFFERENT COLOURS"},
{"hsn":"55162300","description":"OF YARNS OF DIFFERENT COLOURS"},
{"hsn":"551624","description":"PRINTED"},
{"hsn":"55162400","description":"PRINTED"},
{"hsn":"551631","description":"UNBLEACHED OR BLEACHED :"},
{"hsn":"55163110","description":"UNBLEACHED"},
{"hsn":"55163120","description":"BLEACHED"},
{"hsn":"551632","description":"DYED"},
{"hsn":"55163200","description":"DYED"},
{"hsn":"551633","description":"OF YARNS OF DIFFERENT COLOURS"},
{"hsn":"55163300","description":"OF YARNS OF DIFFERENT COLOURS"},
{"hsn":"551634","description":"PRINTED"},
{"hsn":"55163400","description":"PRINTED"},
{"hsn":"551641","description":"UNBLEACHED OR BLEACHED :"},
{"hsn":"55164110","description":"UNBLEACHED"},
{"hsn":"55164120","description":"BLEACHED"},
{"hsn":"551642","description":"DYED"},
{"hsn":"55164200","description":"DYED"},
{"hsn":"551643","description":"OF YARNS OF DIFFERENT COLOURS"},
{"hsn":"55164300","description":"OF YARNS OF DIFFERENT COLOURS"},
{"hsn":"551644","description":"PRINTED"},
{"hsn":"55164400","description":"PRINTED"},
{"hsn":"551691","description":"UNBLEACHED OR BLEACHED :"},
{"hsn":"55169110","description":"UNBLEACHED"},
{"hsn":"55169120","description":"BLEACHED"},
{"hsn":"551692","description":"DYED"},
{"hsn":"55169200","description":"DYED"},
{"hsn":"551693","description":"OF YARNS OF DIFFERENT COLOURS"},
{"hsn":"55169300","description":"OF YARNS OF DIFFERENT COLOURS"},
{"hsn":"551694","description":"PRINTED"},
{"hsn":"55169400","description":"PRINTED"}
]
